plend/__init__.py
plend/models.py
plend/utils.py
plend/presets/__init__.py
plend/presets/poultry.py
plend-0.1.4.dist-info/LICENSE
plend-0.1.4.dist-info/METADATA
plend-0.1.4.dist-info/WHEEL
plend-0.1.4.dist-info/top_level.txt
plend-0.1.4.dist-info/RECORD
