Metadata-Version: 2.1
Name: plend
Version: 0.1.4
Summary: Least Cost Formulation with Python
Home-page: https://github.com/bherbruck/plend
Author: Brennen Herbruck
Author-email: brennen.hrbruck@gmail.com
License: UNKNOWN
Platform: UNKNOWN
Classifier: Programming Language :: Python :: 3
Classifier: License :: OSI Approved :: MIT License
Classifier: Operating System :: OS Independent
Requires-Python: >=3.6
